retuve/__init__.py
retuve/__main__.py
retuve/batch.py
retuve/draw.py
retuve/funcs.py
retuve/testdata.py
retuve/typehints.py
retuve/utils.py
retuve/app/__init__.py
retuve/app/classes.py
retuve/app/helpers.py
retuve/app/utils.py
retuve/app/routes/__init__.py
retuve/app/routes/api.py
retuve/app/routes/live.py
retuve/app/routes/models.py
retuve/app/routes/ui.py
retuve/app/static/download.html
retuve/app/static/index.html
retuve/app/static/live.html
retuve/app/static/main.css
retuve/app/static/main.html
retuve/app/static/upload.html
retuve/classes/__init__.py
retuve/classes/draw.py
retuve/classes/general.py
retuve/classes/metrics.py
retuve/classes/seg.py
retuve/defaults/__init__.py
retuve/defaults/config.py
retuve/defaults/hip_configs.py
retuve/defaults/manual_seg.py
retuve/docs/__init__.py
retuve/docs/modalities/__init__.py
retuve/docs/modalities/ultrasound.py
retuve/docs/modalities/xray.py
retuve/docs/overviews/__init__.py
retuve/docs/overviews/ai_researchers.py
retuve/docs/overviews/clinicians.py
retuve/docs/overviews/developers.py
retuve/docs/usecases/001-bringing-own-dicoms-xray.py
retuve/docs/usecases/002-using-retuve-trak.py
retuve/docs/usecases/003-bringing-own-dicoms-ultrasound.py
retuve/docs/usecases/__init__.py
retuve/files/RobotoMono-Regular.ttf
retuve/hip_us/__init__.py
retuve/hip_us/draw.py
retuve/hip_us/typing.py
retuve/hip_us/classes/__init__.py
retuve/hip_us/classes/dev.py
retuve/hip_us/classes/enums.py
retuve/hip_us/classes/general.py
retuve/hip_us/handlers/__init__.py
retuve/hip_us/handlers/bad_data.py
retuve/hip_us/handlers/segs.py
retuve/hip_us/handlers/side.py
retuve/hip_us/metrics/__init__.py
retuve/hip_us/metrics/aca.py
retuve/hip_us/metrics/alpha.py
retuve/hip_us/metrics/c_ratio.py
retuve/hip_us/metrics/coverage.py
retuve/hip_us/metrics/curvature.py
retuve/hip_us/metrics/dev.py
retuve/hip_us/modes/__init__.py
retuve/hip_us/modes/landmarks.py
retuve/hip_us/modes/seg.py
retuve/hip_us/multiframe/__init__.py
retuve/hip_us/multiframe/graf.py
retuve-1.0.0.dist-info/METADATA
retuve-1.0.0.dist-info/WHEEL
retuve-1.0.0.dist-info/licenses/LICENSE
retuve-1.0.0.dist-info/RECORD
