Metadata-Version: 2.4
Name: retuve
Version: 1.0.0
Author-email: Sharpz7 <adam.mcarthur62@gmail.com>
License-File: LICENSE
Requires-Python: <3.13,>=3.10
Requires-Dist: addict>=2.4.0
Requires-Dist: afterthought>=0.5.0
Requires-Dist: aiohttp>=3.12.14
Requires-Dist: deptry>=0.23.0
Requires-Dist: fastapi>=0.116.1
Requires-Dist: filelock>=3.18.0
Requires-Dist: fire>=0.7.0
Requires-Dist: h11>=0.16.0
Requires-Dist: httpx>=0.28.1
Requires-Dist: jinja2>=3.1.6
Requires-Dist: kaleido>=1.0.0
Requires-Dist: moviepy>=2.2.1
Requires-Dist: open3d>=0.19.0
Requires-Dist: plotly>=6.3.0
Requires-Dist: python-multipart>=0.0.20
Requires-Dist: pyyaml>=6.0.2
Requires-Dist: radstract>=1.0.0
Requires-Dist: requests>=2.32.4
Requires-Dist: scikit-learn>=1.7.1
Requires-Dist: setuptools>=80.9.0
Requires-Dist: starlette>=0.47.2
Requires-Dist: urllib3>=2.5.0
Requires-Dist: uvicorn>=0.35.0
